semiotic_tricks_data_loader/__init__.py
semiotic_tricks_data_loader/commands.py
semiotic_tricks_data_loader/config.py
semiotic_tricks_data_loader/data_loader.py
semiotic_tricks_data_loader/main.py
semiotic_tricks_data_loader/utils/__init__.py
semiotic_tricks_data_loader/utils/command_utils.py
semiotic_tricks_data_loader/utils/exc.py
semiotic_tricks_data_loader/utils/file_extractor.py
semiotic_tricks_data_loader/utils/git.py
semiotic_tricks_data_loader/utils/utils.py
semiotic_tricks_data_loader-0.0.1.dist-info/LICENSE
semiotic_tricks_data_loader-0.0.1.dist-info/WHEEL
semiotic_tricks_data_loader-0.0.1.dist-info/entry_points.txt
semiotic_tricks_data_loader-0.0.1.dist-info/METADATA
semiotic_tricks_data_loader-0.0.1.dist-info/RECORD
